pyuvm/__init__.py
pyuvm/_utils.py
pyuvm/_version.py
pyuvm/error_classes.py
pyuvm/extension_classes.py
pyuvm/s05_base_classes.py
pyuvm/s06_reporting_classes.py
pyuvm/s08_factory_classes.py
pyuvm/s09_phasing.py
pyuvm/s12_uvm_tlm_interfaces.py
pyuvm/s13_predefined_component_classes.py
pyuvm/s13_uvm_component.py
pyuvm/s14_15_python_sequences.py
pyuvm/s17_uvm_reg_enumerations.py
pyuvm/s18_uvm_reg_block.py
pyuvm/s19_uvm_reg_field.py
pyuvm/s20_uvm_reg.py
pyuvm/s21_uvm_reg_map.py
pyuvm/s22_uvm_mem.py
pyuvm/s23_uvm_reg_item.py
pyuvm/s24_uvm_reg_includes.py
pyuvm/s25_uvm_adapter.py
pyuvm/s26_uvm_predictor.py
pyuvm/s27_uvm_reg_pkg.py
pyuvm/utility_classes.py
pyuvm-4.0.0.dist-info/licenses/LICENSE
pyuvm-4.0.0.dist-info/METADATA
pyuvm-4.0.0.dist-info/WHEEL
pyuvm-4.0.0.dist-info/top_level.txt
pyuvm-4.0.0.dist-info/RECORD
