Metadata-Version: 2.4
Name: pyuvm
Version: 4.0.0
Summary: A Python implementation of the UVM using cocotb
Home-page: https://github.com/pyuvm/pyuvm
Author: Ray Salemi
Author-email: ray@raysalemi.com
Project-URL: Bug Tracker, https://github.com/pyuvm/pyuvm/issues
Classifier: Programming Language :: Python :: 3
Classifier: License :: OSI Approved :: Apache Software License
Classifier: Operating System :: OS Independent
Classifier: Topic :: Scientific/Engineering :: Electronic Design Automation (EDA)
Classifier: Framework :: cocotb
Requires-Python: >=3.6
License-File: LICENSE
Requires-Dist: cocotb<3.0,>=1.6.0
Provides-Extra: dev
Requires-Dist: tox; extra == "dev"
Requires-Dist: pre-commit; extra == "dev"
Requires-Dist: pytest; extra == "dev"
Requires-Dist: ruff; extra == "dev"
Dynamic: author
Dynamic: author-email
Dynamic: classifier
Dynamic: description
Dynamic: description-content-type
Dynamic: home-page
Dynamic: license-file
Dynamic: project-url
Dynamic: provides-extra
Dynamic: requires-dist
Dynamic: requires-python
Dynamic: summary
